bbcli/__init__.py
bbcli/__main__.py
bbcli/__version__.py
bbcli/cli.py
bbcli/commands/__init__.py
bbcli/commands/announcements.py
bbcli/commands/assignments.py
bbcli/commands/contents.py
bbcli/commands/courses.py
bbcli/entities/Node.py
bbcli/entities/RequestData.py
bbcli/entities/__init__.py
bbcli/entities/content_builder_entitites.py
bbcli/services/__init__.py
bbcli/services/announcements_services.py
bbcli/services/assignments_services.py
bbcli/services/authorization_service.py
bbcli/services/contents_services.py
bbcli/services/courses_services.py
bbcli/services/utils/__init__.py
bbcli/services/utils/attempt_builder.py
bbcli/services/utils/content_builder.py
bbcli/utils/URL_builder.py
bbcli/utils/__init__.py
bbcli/utils/content_handler.py
bbcli/utils/content_utils.py
bbcli/utils/error_handler.py
bbcli/utils/utils.py
bbcli/views/__init__.py
bbcli/views/announcements_views.py
bbcli/views/assignments_views.py
bbcli/views/contents_views.py
bbcli/views/courses_views.py
Blackboard_LMS_CLI-1.0.9.dist-info/LICENSE
Blackboard_LMS_CLI-1.0.9.dist-info/METADATA
Blackboard_LMS_CLI-1.0.9.dist-info/WHEEL
Blackboard_LMS_CLI-1.0.9.dist-info/entry_points.txt
Blackboard_LMS_CLI-1.0.9.dist-info/top_level.txt
Blackboard_LMS_CLI-1.0.9.dist-info/RECORD
