Metadata-Version: 2.1
Name: Blackboard-LMS-CLI
Version: 1.0.9
Summary: A command-line tool suite for communicating with the Blackboard Learn Managment System
Home-page: https://github.com/Magnus2142/Blackboard-LMS-CLI
Author: Hans William Forebrigd, Mattias Aggentoft Eggen, Magnus Bredeli
Author-email: hansw0701@gmail.com, mattias.a.eggen@gmail.com, magnus.bredeli@hotmail.com
License: Willyeh Wonkmeh 2.0
Platform: UNKNOWN
Requires-Dist: Click (>=8.1)
Requires-Dist: colorama
Requires-Dist: requests
Requires-Dist: python-dotenv
Requires-Dist: beautifulsoup4
Requires-Dist: lxml (>=4.8.0)
Requires-Dist: shellingham
Requires-Dist: anytree
Requires-Dist: html2text
Requires-Dist: python-dateutil
Requires-Dist: tabulate (==0.8.9)
Requires-Dist: pwinput
Requires-Dist: Markdown (==3.3.6)
Requires-Dist: markdownify (==0.11.2)
